LICENSE
MANIFEST.in
README.rst
setup.py
nginxparser_eb/__init__.py
nginxparser_eb.egg-info/PKG-INFO
nginxparser_eb.egg-info/SOURCES.txt
nginxparser_eb.egg-info/dependency_links.txt
nginxparser_eb.egg-info/requires.txt
nginxparser_eb.egg-info/top_level.txt
nginxparser_eb/tests/__init__.py
nginxparser_eb/tests/nginxparser_test.py
nginxparser_eb/tests/test_data/etc_nginx/complex.conf