Metadata-Version: 1.1
Name: nginxparser-eb
Version: 0.0.8
Summary: Nginx configuration Parser
Home-page: https://github.com/EnigmaBridge/nginxparser
Author: Dusan Klinec
Author-email: dusan.klinec@gmail.com
License: The MIT License (MIT)
